nichexpert/__init__.py
nichexpert/analysis/__init__.py
nichexpert/analysis/_utils.py
nichexpert/plot/__init__.py
nichexpert/plot/_utils.py
nichexpert/plot/palettes.py
nichexpert/preprocess/__init__.py
nichexpert/preprocess/_build.py
nichexpert/preprocess/_utils.py
nichexpert/trainer/__init__.py
nichexpert/trainer/_model.py
nichexpert/trainer/_train.py
nichexpert/trainer/_utils.py
nichexpert-0.1.2.dist-info/LICENSE
nichexpert-0.1.2.dist-info/METADATA
nichexpert-0.1.2.dist-info/WHEEL
nichexpert-0.1.2.dist-info/top_level.txt
nichexpert-0.1.2.dist-info/RECORD
