Metadata-Version: 2.1
Name: nichexpert
Version: 0.1.2
Summary: A tool to identify niche for spatial transcriptomics data.
Home-page: https://github.com/YANG-ERA/NicheXpert
Author: Jiyuan Yang
Author-email: 599568651@qq.com
License: MIT
Requires-Python: >=3.11
License-File: LICENSE
Requires-Dist: anndata (>=0.10.9)
Requires-Dist: matplotlib (>=3.7.3)
Requires-Dist: numpy (>=1.23.4)
Requires-Dist: pandas (>=2.1.0)
Requires-Dist: scanpy (>=1.9.8)
Requires-Dist: scikit-learn (>=1.4.1.post1)
Requires-Dist: scipy (>=1.12.0)
Requires-Dist: seaborn (>=0.13.2)
Requires-Dist: squidpy (>=1.4.1)
Requires-Dist: tqdm (>=4.67.1)
Requires-Dist: pydantic (>=2.12.2)
